{
  "cabins": {
    "sc-beaufort-port-royal-farmers-market": {
      "state": "Georgia",
      "city": "Helen",
      "name": "Private Room in Nature Lodge",
      "link": "https://www.airbnb.com/rooms/32688024",
      "rating": "★ 4.86 · 111 reviews",
      "imageSrc": "https://a0.muscache.com/im/pictures/ea105376-0558-42e4-aacb-2201576fde1a.jpg?im_w=480&sw_cache=trips_images",
      "description": [
        "Elegant mountainside retreat in gated golf community. Downtown Helen is less than five minutes.Professionally remodeled Bathroom with huge, gorgeous new shower. Just completed in August 2020.Refreshment station includes refrigerator, microwave, and Keurig coffee maker. Private balcony with beautiful Mountain views. Enjoy the serenity of the Chattahoochee National Forest. Wrap yourself in our new 800 thread count Linen and our luxurious new bath sheets."
      ]
    }
  }
}
